{
    "kind":  "sketchcatch_git_cicd_auto_deploy_smoke",
    "mode":  "preflight",
    "status":  "blocked",
    "handoffId":  "",
    "startedAt":  "2026-07-07T07:56:54.3314550Z",
    "finishedAt":  "2026-07-07T07:56:54.4714982Z",
    "pipelineStatus":  null,
    "steps":  [
                  {
                      "name":  "api_health",
                      "status":  "passed",
                      "evidence":  "HTTP 200"
                  },
                  {
                      "name":  "access_token",
                      "status":  "blocked",
                      "evidence":  "AccessToken is required for live smoke API calls"
                  },
                  {
                      "name":  "handoff_id",
                      "status":  "blocked",
                      "evidence":  "HandoffId is required for live smoke API calls"
                  },
                  {
                      "name":  "live_mutation_approval",
                      "status":  "skipped",
                      "evidence":  "Mutation steps are skipped"
                  },
                  {
                      "name":  "pipeline_success_gate",
                      "status":  "skipped",
                      "evidence":  "RequirePipelineSuccess was not set"
                  },
                  {
                      "name":  "destroy_success_gate",
                      "status":  "skipped",
                      "evidence":  "RequireDestroySuccess was not set"
                  }
              ]
}
